{
  "schema_version": 3,
  "ts": "2026-05-31T21:56:06.963Z",
  "bucket_start_utc": "2026-05-31T21:00:00.000Z",
  "bucket_end_utc": "2026-06-01T00:00:00.000Z",
  "bucket_hours": 3,
  "source": {
    "type": "github_issues",
    "owner": "mowlsint",
    "repo": "MagicPaws",
    "state": "open"
  },
  "counts": {
    "open_events_total": 1000,
    "open_events_deduped_total": 936,
    "recent_72h_events": 134,
    "recent_72h_deduped_events": 128,
    "recent_72h_source_capped_weighted_events": 38.58,
    "current_bucket_events": 3,
    "current_bucket_deduped_events": 3,
    "current_bucket_source_capped_weighted_events": 3,
    "duplicate_events_total": 64,
    "duplicate_events_72h": 6,
    "duplicate_events_bucket": 0,
    "social_rss_events_72h": 134,
    "social_rss_deduped_events_72h": 128,
    "social_rss_events_bucket": 3,
    "social_rss_deduped_events_bucket": 3,
    "p0_suspect_72h": 1,
    "geo_total": 94,
    "geo_72h": 11,
    "geo_count_method": "explicit_coordinates_or_controlled_candidates"
  },
  "sensors": {
    "hybrid_seismograph_pct": 5,
    "hybrid_window_hours": 6,
    "hybrid_72h_peak_pct": 13,
    "hybrid_windows_pct": {
      "6": 5,
      "12": 3,
      "24": 2,
      "48": 2
    },
    "keyword_barometer_pct": 3,
    "government_weirdness": {
      "north_sea_pct": 6,
      "baltic_sea_pct": 2
    }
  },
  "diagnostics": {
    "scoring_input_note": "Sensor scores use deduped events plus source caps. Raw counts remain available for baseline analysis.",
    "source_cap_profile": {
      "social": [
        1,
        0.45,
        0.2,
        0.08
      ],
      "rss": [
        1,
        0.65,
        0.35,
        0.15
      ],
      "media": [
        1,
        0.75,
        0.5,
        0.25
      ],
      "official": [
        1,
        0.9,
        0.75,
        0.5
      ],
      "osint": [
        1,
        0.6,
        0.3,
        0.12
      ],
      "unknown": [
        1,
        0.5,
        0.2,
        0.08
      ]
    },
    "hybrid_weighted_points_72h": 35.11,
    "hybrid_hourly_buckets_72h": [
      {
        "idx": 0,
        "points": 1.31,
        "pct": 5,
        "events": 6
      },
      {
        "idx": 1,
        "points": 0.3,
        "pct": 1,
        "events": 2
      },
      {
        "idx": 2,
        "points": 0.21,
        "pct": 1,
        "events": 2
      },
      {
        "idx": 3,
        "points": 0.15,
        "pct": 1,
        "events": 1
      },
      {
        "idx": 4,
        "points": 0.15,
        "pct": 1,
        "events": 1
      },
      {
        "idx": 5,
        "points": 0.15,
        "pct": 1,
        "events": 1
      },
      {
        "idx": 6,
        "points": 0.15,
        "pct": 1,
        "events": 2
      },
      {
        "idx": 7,
        "points": 0,
        "pct": 0,
        "events": 0
      },
      {
        "idx": 8,
        "points": 0,
        "pct": 0,
        "events": 0
      },
      {
        "idx": 9,
        "points": 0,
        "pct": 0,
        "events": 0
      },
      {
        "idx": 10,
        "points": 3.7,
        "pct": 13,
        "events": 12
      },
      {
        "idx": 11,
        "points": 0.88,
        "pct": 3,
        "events": 2
      },
      {
        "idx": 12,
        "points": 0,
        "pct": 0,
        "events": 0
      },
      {
        "idx": 13,
        "points": 0,
        "pct": 0,
        "events": 0
      },
      {
        "idx": 14,
        "points": 1.01,
        "pct": 4,
        "events": 9
      },
      {
        "idx": 15,
        "points": 0,
        "pct": 0,
        "events": 0
      },
      {
        "idx": 16,
        "points": 0,
        "pct": 0,
        "events": 0
      },
      {
        "idx": 17,
        "points": 0,
        "pct": 0,
        "events": 0
      },
      {
        "idx": 18,
        "points": 3.67,
        "pct": 13,
        "events": 14
      },
      {
        "idx": 19,
        "points": 0.3,
        "pct": 1,
        "events": 2
      },
      {
        "idx": 20,
        "points": 0.15,
        "pct": 1,
        "events": 1
      },
      {
        "idx": 21,
        "points": 1.37,
        "pct": 5,
        "events": 6
      },
      {
        "idx": 22,
        "points": 0.15,
        "pct": 1,
        "events": 1
      },
      {
        "idx": 23,
        "points": 0.9,
        "pct": 3,
        "events": 7
      },
      {
        "idx": 24,
        "points": 0.75,
        "pct": 3,
        "events": 6
      },
      {
        "idx": 25,
        "points": 0,
        "pct": 0,
        "events": 0
      },
      {
        "idx": 26,
        "points": 0.32,
        "pct": 1,
        "events": 3
      },
      {
        "idx": 27,
        "points": 0,
        "pct": 0,
        "events": 0
      },
      {
        "idx": 28,
        "points": 0.36,
        "pct": 1,
        "events": 1
      },
      {
        "idx": 29,
        "points": 0,
        "pct": 0,
        "events": 0
      },
      {
        "idx": 30,
        "points": 0.8,
        "pct": 3,
        "events": 1
      },
      {
        "idx": 31,
        "points": 0,
        "pct": 0,
        "events": 0
      },
      {
        "idx": 32,
        "points": 0,
        "pct": 0,
        "events": 0
      },
      {
        "idx": 33,
        "points": 0.8,
        "pct": 3,
        "events": 1
      },
      {
        "idx": 34,
        "points": 0,
        "pct": 0,
        "events": 0
      },
      {
        "idx": 35,
        "points": 0.33,
        "pct": 1,
        "events": 3
      },
      {
        "idx": 36,
        "points": 0,
        "pct": 0,
        "events": 0
      },
      {
        "idx": 37,
        "points": 0.72,
        "pct": 3,
        "events": 4
      },
      {
        "idx": 38,
        "points": 0,
        "pct": 0,
        "events": 0
      },
      {
        "idx": 39,
        "points": 0,
        "pct": 0,
        "events": 0
      },
      {
        "idx": 40,
        "points": 0.12,
        "pct": 0,
        "events": 1
      },
      {
        "idx": 41,
        "points": 0.06,
        "pct": 0,
        "events": 1
      },
      {
        "idx": 42,
        "points": 0,
        "pct": 0,
        "events": 0
      },
      {
        "idx": 43,
        "points": 1.23,
        "pct": 4,
        "events": 4
      },
      {
        "idx": 44,
        "points": 0.27,
        "pct": 1,
        "events": 2
      },
      {
        "idx": 45,
        "points": 1.61,
        "pct": 6,
        "events": 3
      },
      {
        "idx": 46,
        "points": 0.2,
        "pct": 1,
        "events": 2
      },
      {
        "idx": 47,
        "points": 0.69,
        "pct": 2,
        "events": 4
      },
      {
        "idx": 48,
        "points": 0.08,
        "pct": 0,
        "events": 1
      },
      {
        "idx": 49,
        "points": 0,
        "pct": 0,
        "events": 0
      },
      {
        "idx": 50,
        "points": 0,
        "pct": 0,
        "events": 0
      },
      {
        "idx": 51,
        "points": 0,
        "pct": 0,
        "events": 0
      },
      {
        "idx": 52,
        "points": 0,
        "pct": 0,
        "events": 0
      },
      {
        "idx": 53,
        "points": 0,
        "pct": 0,
        "events": 0
      },
      {
        "idx": 54,
        "points": 0.43,
        "pct": 2,
        "events": 1
      },
      {
        "idx": 55,
        "points": 0,
        "pct": 0,
        "events": 0
      },
      {
        "idx": 56,
        "points": 0,
        "pct": 0,
        "events": 0
      },
      {
        "idx": 57,
        "points": 0.88,
        "pct": 3,
        "events": 2
      },
      {
        "idx": 58,
        "points": 0.08,
        "pct": 0,
        "events": 1
      },
      {
        "idx": 59,
        "points": 0,
        "pct": 0,
        "events": 0
      },
      {
        "idx": 60,
        "points": 0.21,
        "pct": 1,
        "events": 1
      },
      {
        "idx": 61,
        "points": 0.48,
        "pct": 2,
        "events": 1
      },
      {
        "idx": 62,
        "points": 0,
        "pct": 0,
        "events": 0
      },
      {
        "idx": 63,
        "points": 0,
        "pct": 0,
        "events": 0
      },
      {
        "idx": 64,
        "points": 1.18,
        "pct": 4,
        "events": 2
      },
      {
        "idx": 65,
        "points": 0,
        "pct": 0,
        "events": 0
      },
      {
        "idx": 66,
        "points": 2.17,
        "pct": 8,
        "events": 4
      },
      {
        "idx": 67,
        "points": 0.8,
        "pct": 3,
        "events": 2
      },
      {
        "idx": 68,
        "points": 1.6,
        "pct": 6,
        "events": 2
      },
      {
        "idx": 69,
        "points": 0.35,
        "pct": 1,
        "events": 1
      },
      {
        "idx": 70,
        "points": 1.25,
        "pct": 4,
        "events": 1
      },
      {
        "idx": 71,
        "points": 2.76,
        "pct": 10,
        "events": 3
      }
    ],
    "keyword_weighted_hits_bucket": 0.7,
    "keyword_raw_hits_bucket": 1,
    "keyword_scored_events_bucket": 3,
    "government_weirdness_north_sea_points": 2.17,
    "government_weirdness_baltic_sea_points": 0.86,
    "government_weirdness_north_sea_events": 5,
    "government_weirdness_baltic_sea_events": 3,
    "government_weirdness_north_sea_weighted_events": 1.81,
    "government_weirdness_baltic_sea_weighted_events": 1.35,
    "keyword_config_loaded": true,
    "keyword_config_version": 2,
    "cold_start_note": "Scores are cold-start density values until a 90-day baseline exists."
  },
  "top_terms": [
    {
      "term": "KRITIS",
      "tier": "B",
      "count": 1,
      "weighted": 0.7
    }
  ],
  "top_sources_72h": [
    {
      "source_id": "The Maritime Executive",
      "count": 26
    },
    {
      "source_id": "gcaptain_rss",
      "count": 20
    },
    {
      "source_id": "auonsson_bsky",
      "count": 16
    },
    {
      "source_id": "warontherocks_bsky",
      "count": 16
    },
    {
      "source_id": "small_wars_journal_rss",
      "count": 12
    },
    {
      "source_id": "worldcrimeintel_x",
      "count": 7
    },
    {
      "source_id": "warshipcam_x",
      "count": 7
    },
    {
      "source_id": "tom_sharpe_x",
      "count": 5
    },
    {
      "source_id": "oiuye_bsky",
      "count": 5
    },
    {
      "source_id": "maritimekiwi_bsky",
      "count": 5
    },
    {
      "source_id": "cepa_feed",
      "count": 3
    },
    {
      "source_id": "rusi_latest_publications",
      "count": 3
    }
  ],
  "top_sources_72h_deduped": [
    {
      "source_id": "The Maritime Executive",
      "count": 26
    },
    {
      "source_id": "gcaptain_rss",
      "count": 19
    },
    {
      "source_id": "warontherocks_bsky",
      "count": 15
    },
    {
      "source_id": "auonsson_bsky",
      "count": 14
    },
    {
      "source_id": "small_wars_journal_rss",
      "count": 11
    },
    {
      "source_id": "worldcrimeintel_x",
      "count": 7
    },
    {
      "source_id": "warshipcam_x",
      "count": 7
    },
    {
      "source_id": "tom_sharpe_x",
      "count": 5
    },
    {
      "source_id": "oiuye_bsky",
      "count": 5
    },
    {
      "source_id": "maritimekiwi_bsky",
      "count": 4
    },
    {
      "source_id": "cepa_feed",
      "count": 3
    },
    {
      "source_id": "rusi_latest_publications",
      "count": 3
    }
  ],
  "domain_counts_72h": {
    "D:AIS_TRACK": 7,
    "D:INCIDENT": 4,
    "D:INFRA_CI": 14,
    "D:NEWS_INTEL": 85,
    "D:RF_SIGNAL": 16,
    "D:SECURITY_CRIME": 8
  },
  "domain_counts_72h_deduped": {
    "D:AIS_TRACK": 7,
    "D:INCIDENT": 4,
    "D:INFRA_CI": 14,
    "D:NEWS_INTEL": 81,
    "D:RF_SIGNAL": 14,
    "D:SECURITY_CRIME": 8
  },
  "region_counts_72h": {
    "REG:ATLANTIC_NE": 5,
    "REG:BALTIC": 1,
    "REG:EUROPE": 8,
    "REG:GLOBAL": 19,
    "REG:NORTH_SEA": 5,
    "REG:OTHER": 70,
    "REG:UNKNOWN": 26
  },
  "region_counts_72h_deduped": {
    "REG:ATLANTIC_NE": 5,
    "REG:BALTIC": 1,
    "REG:EUROPE": 8,
    "REG:GLOBAL": 18,
    "REG:NORTH_SEA": 5,
    "REG:OTHER": 65,
    "REG:UNKNOWN": 26
  },
  "baseline_observations": {
    "note": "Raw baseline observations for later 90-day normalization. Scores are not yet baseline-normalized.",
    "source_kind_counts_bucket": {
      "social": 3
    },
    "source_kind_counts_bucket_deduped": {
      "social": 3
    },
    "source_kind_counts_72h": {
      "rss": 67,
      "social": 67
    },
    "source_kind_counts_72h_deduped": {
      "rss": 65,
      "social": 63
    },
    "source_domain_counts_bucket": {
      "tom_sharpe_x|D:INFRA_CI": 1,
      "warshipcam_x|D:AIS_TRACK": 1,
      "worldcrimeintel_x|D:SECURITY_CRIME": 1
    },
    "source_domain_counts_bucket_deduped": {
      "tom_sharpe_x|D:INFRA_CI": 1,
      "warshipcam_x|D:AIS_TRACK": 1,
      "worldcrimeintel_x|D:SECURITY_CRIME": 1
    },
    "source_domain_counts_72h": {
      "atlantic_council_reports|D:INFRA_CI": 1,
      "auonsson_bsky|D:RF_SIGNAL": 16,
      "cepa_feed|D:INFRA_CI": 3,
      "die_flaschenpost_rss|D:NEWS_INTEL": 1,
      "gcaptain_rss|D:NEWS_INTEL": 20,
      "highnorthnews_bsky|D:NEWS_INTEL": 3,
      "ispk_bsky|D:NEWS_INTEL": 1,
      "maritimekiwi_bsky|D:NEWS_INTEL": 5,
      "navylookout_bsky|D:NEWS_INTEL": 2,
      "oiuye_bsky|D:NEWS_INTEL": 5,
      "rusi_latest_publications|D:INFRA_CI": 3,
      "small_wars_journal_rss|D:NEWS_INTEL": 12,
      "swp_publications_de|D:INFRA_CI": 1,
      "The Maritime Executive|D:INCIDENT": 4,
      "The Maritime Executive|D:INFRA_CI": 1,
      "The Maritime Executive|D:NEWS_INTEL": 20,
      "The Maritime Executive|D:SECURITY_CRIME": 1,
      "tom_sharpe_x|D:INFRA_CI": 5,
      "warontherocks_bsky|D:NEWS_INTEL": 16,
      "warshipcam_x|D:AIS_TRACK": 7,
      "worldcrimeintel_x|D:SECURITY_CRIME": 7
    },
    "source_domain_counts_72h_deduped": {
      "atlantic_council_reports|D:INFRA_CI": 1,
      "auonsson_bsky|D:RF_SIGNAL": 14,
      "cepa_feed|D:INFRA_CI": 3,
      "die_flaschenpost_rss|D:NEWS_INTEL": 1,
      "gcaptain_rss|D:NEWS_INTEL": 19,
      "highnorthnews_bsky|D:NEWS_INTEL": 3,
      "ispk_bsky|D:NEWS_INTEL": 1,
      "maritimekiwi_bsky|D:NEWS_INTEL": 4,
      "navylookout_bsky|D:NEWS_INTEL": 2,
      "oiuye_bsky|D:NEWS_INTEL": 5,
      "rusi_latest_publications|D:INFRA_CI": 3,
      "small_wars_journal_rss|D:NEWS_INTEL": 11,
      "swp_publications_de|D:INFRA_CI": 1,
      "The Maritime Executive|D:INCIDENT": 4,
      "The Maritime Executive|D:INFRA_CI": 1,
      "The Maritime Executive|D:NEWS_INTEL": 20,
      "The Maritime Executive|D:SECURITY_CRIME": 1,
      "tom_sharpe_x|D:INFRA_CI": 5,
      "warontherocks_bsky|D:NEWS_INTEL": 15,
      "warshipcam_x|D:AIS_TRACK": 7,
      "worldcrimeintel_x|D:SECURITY_CRIME": 7
    },
    "source_region_counts_72h": {
      "atlantic_council_reports|REG:EUROPE": 1,
      "auonsson_bsky|REG:OTHER": 16,
      "cepa_feed|REG:EUROPE": 3,
      "die_flaschenpost_rss|REG:OTHER": 1,
      "gcaptain_rss|REG:OTHER": 20,
      "highnorthnews_bsky|REG:ATLANTIC_NE": 3,
      "ispk_bsky|REG:BALTIC": 1,
      "maritimekiwi_bsky|REG:OTHER": 5,
      "navylookout_bsky|REG:ATLANTIC_NE": 2,
      "oiuye_bsky|REG:OTHER": 5,
      "rusi_latest_publications|REG:EUROPE": 3,
      "small_wars_journal_rss|REG:GLOBAL": 12,
      "swp_publications_de|REG:EUROPE": 1,
      "The Maritime Executive|REG:UNKNOWN": 26,
      "tom_sharpe_x|REG:NORTH_SEA": 5,
      "warontherocks_bsky|REG:OTHER": 16,
      "warshipcam_x|REG:GLOBAL": 7,
      "worldcrimeintel_x|REG:OTHER": 7
    },
    "source_region_counts_72h_deduped": {
      "atlantic_council_reports|REG:EUROPE": 1,
      "auonsson_bsky|REG:OTHER": 14,
      "cepa_feed|REG:EUROPE": 3,
      "die_flaschenpost_rss|REG:OTHER": 1,
      "gcaptain_rss|REG:OTHER": 19,
      "highnorthnews_bsky|REG:ATLANTIC_NE": 3,
      "ispk_bsky|REG:BALTIC": 1,
      "maritimekiwi_bsky|REG:OTHER": 4,
      "navylookout_bsky|REG:ATLANTIC_NE": 2,
      "oiuye_bsky|REG:OTHER": 5,
      "rusi_latest_publications|REG:EUROPE": 3,
      "small_wars_journal_rss|REG:GLOBAL": 11,
      "swp_publications_de|REG:EUROPE": 1,
      "The Maritime Executive|REG:UNKNOWN": 26,
      "tom_sharpe_x|REG:NORTH_SEA": 5,
      "warontherocks_bsky|REG:OTHER": 15,
      "warshipcam_x|REG:GLOBAL": 7,
      "worldcrimeintel_x|REG:OTHER": 7
    },
    "duplicate_sources_bucket": {},
    "duplicate_sources_72h": {
      "auonsson_bsky": 2,
      "gcaptain_rss": 1,
      "maritimekiwi_bsky": 1,
      "small_wars_journal_rss": 1,
      "warontherocks_bsky": 1
    },
    "source_caps_bucket": [
      {
        "source_id": "tom_sharpe_x",
        "source_kind": "social",
        "raw_events": 1,
        "weighted_events": 1,
        "capped_events": 0
      },
      {
        "source_id": "warshipcam_x",
        "source_kind": "social",
        "raw_events": 1,
        "weighted_events": 1,
        "capped_events": 0
      },
      {
        "source_id": "worldcrimeintel_x",
        "source_kind": "social",
        "raw_events": 1,
        "weighted_events": 1,
        "capped_events": 0
      }
    ],
    "source_caps_72h": [
      {
        "source_id": "The Maritime Executive",
        "source_kind": "rss",
        "raw_events": 26,
        "weighted_events": 5.45,
        "capped_events": 25
      },
      {
        "source_id": "gcaptain_rss",
        "source_kind": "rss",
        "raw_events": 19,
        "weighted_events": 4.4,
        "capped_events": 18
      },
      {
        "source_id": "warontherocks_bsky",
        "source_kind": "social",
        "raw_events": 15,
        "weighted_events": 2.61,
        "capped_events": 14
      },
      {
        "source_id": "auonsson_bsky",
        "source_kind": "social",
        "raw_events": 14,
        "weighted_events": 2.53,
        "capped_events": 13
      },
      {
        "source_id": "small_wars_journal_rss",
        "source_kind": "rss",
        "raw_events": 11,
        "weighted_events": 3.2,
        "capped_events": 10
      },
      {
        "source_id": "warshipcam_x",
        "source_kind": "social",
        "raw_events": 7,
        "weighted_events": 1.97,
        "capped_events": 6
      },
      {
        "source_id": "worldcrimeintel_x",
        "source_kind": "social",
        "raw_events": 7,
        "weighted_events": 1.97,
        "capped_events": 6
      },
      {
        "source_id": "oiuye_bsky",
        "source_kind": "social",
        "raw_events": 5,
        "weighted_events": 1.81,
        "capped_events": 4
      },
      {
        "source_id": "tom_sharpe_x",
        "source_kind": "social",
        "raw_events": 5,
        "weighted_events": 1.81,
        "capped_events": 4
      },
      {
        "source_id": "maritimekiwi_bsky",
        "source_kind": "social",
        "raw_events": 4,
        "weighted_events": 1.73,
        "capped_events": 3
      },
      {
        "source_id": "cepa_feed",
        "source_kind": "rss",
        "raw_events": 3,
        "weighted_events": 2,
        "capped_events": 2
      },
      {
        "source_id": "highnorthnews_bsky",
        "source_kind": "social",
        "raw_events": 3,
        "weighted_events": 1.65,
        "capped_events": 2
      },
      {
        "source_id": "rusi_latest_publications",
        "source_kind": "rss",
        "raw_events": 3,
        "weighted_events": 2,
        "capped_events": 2
      },
      {
        "source_id": "navylookout_bsky",
        "source_kind": "social",
        "raw_events": 2,
        "weighted_events": 1.45,
        "capped_events": 1
      },
      {
        "source_id": "atlantic_council_reports",
        "source_kind": "rss",
        "raw_events": 1,
        "weighted_events": 1,
        "capped_events": 0
      },
      {
        "source_id": "die_flaschenpost_rss",
        "source_kind": "rss",
        "raw_events": 1,
        "weighted_events": 1,
        "capped_events": 0
      },
      {
        "source_id": "ispk_bsky",
        "source_kind": "social",
        "raw_events": 1,
        "weighted_events": 1,
        "capped_events": 0
      },
      {
        "source_id": "swp_publications_de",
        "source_kind": "rss",
        "raw_events": 1,
        "weighted_events": 1,
        "capped_events": 0
      }
    ]
  }
}
